suletree/__init__.py
suletree-0.1.0.dist-info/METADATA
suletree-0.1.0.dist-info/WHEEL
suletree-0.1.0.dist-info/entry_points.txt
suletree-0.1.0.dist-info/RECORD
